serial_weaver/__init__.py
serial_weaver/config.py
serial_weaver/custom_collections.py
serial_weaver/datastore.py
serial_weaver/dumpers.py
serial_weaver/exceptions.py
serial_weaver/loaders.py
serial_weaver/models.py
serial_weaver/tests/__init__.py
serial_weaver/tests/converting.py
serial_weaver/tests/mocked_data/customers.json
serial_weaver/tests/mocked_data/customers.toml
serial_weaver/tests/mocked_data/customers.yaml
serial_weaver/tests/mocked_data/customers.yml
serial_weaver/tests/mocked_data/products.yaml
serial_weaver/tests/mocked_data/rendered_customers.txt
serial_weaver/tests/mocked_data/yml_customers.yaml
serial_weaver/tests/models.py
serial_weaver/tests/templates/customer.j2
serial_weaver/tests/test_data_conversion.py
serial_weaver/tests/test_models.py
serial_weaver/tests/utils.py
serial_weaver/utils.py
serial_weaver-0.1.0.dist-info/LICENSE
serial_weaver-0.1.0.dist-info/METADATA
serial_weaver-0.1.0.dist-info/WHEEL
serial_weaver-0.1.0.dist-info/RECORD
